{
  "gitSyncId": "f725fd45-c84b-4cc9-9a33-9bac5fa61591_1d580748-ac15-4639-971f-05af0cb5b742",
  "unpublishedPage": {
    "layouts": [
      {
        "dsl": {
          "backgroundColor": "none",
          "bottomRow": 5000,
          "canExtend": true,
          "containerStyle": "none",
          "detachFromLayout": true,
          "dynamicBindingPathList": [],
          "dynamicTriggerPathList": [],
          "leftColumn": 0,
          "minHeight": 1292,
          "parentColumnSpace": 1,
          "parentRowSpace": 1,
          "rightColumn": 4896,
          "snapColumns": 64,
          "snapRows": 124,
          "topRow": 0,
          "type": "CANVAS_WIDGET",
          "version": 90,
          "widgetId": "0",
          "widgetName": "MainContainer"
        }
      }
    ],
    "name": "Page1",
    "slug": "page1"
  }
}